mcp_server_twelve_data/__init__.py
mcp_server_twelve_data/__main__.py
mcp_server_twelve_data/common.py
mcp_server_twelve_data/doc_tool.py
mcp_server_twelve_data/doc_tool_remote.py
mcp_server_twelve_data/doc_tool_response.py
mcp_server_twelve_data/key_provider.py
mcp_server_twelve_data/prompts.py
mcp_server_twelve_data/request_models.py
mcp_server_twelve_data/response_models.py
mcp_server_twelve_data/server.py
mcp_server_twelve_data/tools.py
mcp_server_twelve_data/u_tool.py
mcp_server_twelve_data/u_tool_remote.py
mcp_server_twelve_data/u_tool_response.py
mcp_server_twelve_data-0.2.5.dist-info/METADATA
mcp_server_twelve_data-0.2.5.dist-info/WHEEL
mcp_server_twelve_data-0.2.5.dist-info/entry_points.txt
mcp_server_twelve_data-0.2.5.dist-info/licenses/LICENSE
mcp_server_twelve_data-0.2.5.dist-info/RECORD
