Metadata-Version: 2.4
Name: mcp-server-twelve-data
Version: 0.2.5
Summary: A Model Context Protocol server providing tools access Twelve Data.
Author: Twelve Data, PBC.
Maintainer-email: Kopyev Eugene <kopyev.eugene@gmail.com>
License: MIT
License-File: LICENSE
Keywords: automation,data,llm,mcp,twelve
Classifier: Development Status :: 4 - Beta
Classifier: Intended Audience :: Developers
Classifier: License :: OSI Approved :: MIT License
Classifier: Programming Language :: Python :: 3
Classifier: Programming Language :: Python :: 3.13
Requires-Python: >=3.13
Requires-Dist: click==8.2.1
Requires-Dist: mcp[cli]>=1.9.4
Requires-Dist: openai>=1.86.0
Requires-Dist: pydantic==2.11.5
Requires-Dist: pylint>=3.3.7
Requires-Dist: pyyml>=0.0.2
Provides-Extra: db
Requires-Dist: lancedb>=0.23.0; extra == 'db'
Requires-Dist: pandas>=2.3.1; extra == 'db'
